{
  "startedAt": "2026-03-19T10:42:16.457Z",
  "lastUpdatedAt": "2026-03-20T06:03:59.989Z",
  "capital": 5000,
  "strategyA": {
    "name": "Max APY",
    "positions": [
      {
        "chain": "Base",
        "project": "uniswap-v4",
        "symbol": "ETH-USDC",
        "tvlUsd": 1640306,
        "apyBase": 70.1977,
        "apyReward": null,
        "apy": 70.1977,
        "rewardTokens": null,
        "pool": "642f316f-f3bf-414b-9536-122c688831e0",
        "apyPct1D": -4.72042,
        "apyPct7D": -9.86504,
        "apyPct30D": 44.5539,
        "stablecoin": false,
        "ilRisk": "yes",
        "exposure": "multi",
        "predictions": {
          "predictedClass": "Down",
          "predictedProbability": 99,
          "binnedConfidence": 3
        },
        "poolMeta": "0.30%",
        "mu": 41.87315,
        "sigma": 1.18428,
        "count": 56,
        "outlier": true,
        "underlyingTokens": [
          "0x0000000000000000000000000000000000000000",
          "0x833589fcd6edb6e08f4c7c32d4f71b54bda02913"
        ],
        "il7d": null,
        "apyBase7d": null,
        "apyMean30d": 56.92644,
        "volumeUsd1d": 1051559.00437,
        "volumeUsd7d": null,
        "apyBaseInception": null,
        "type": "lp",
        "weight": 0.2
      },
      {
        "chain": "Solana",
        "project": "orca-dex",
        "symbol": "SOL-USDC",
        "tvlUsd": 29462739,
        "apyBase": 68.52923,
        "apyReward": 0,
        "apy": 68.52923,
        "rewardTokens": null,
        "pool": "a5c85bc8-eb41-45c0-a520-d18d7529c0d8",
        "apyPct1D": -6.00466,
        "apyPct7D": -18.17925,
        "apyPct30D": -2.88982,
        "stablecoin": false,
        "ilRisk": "yes",
        "exposure": "multi",
        "predictions": {
          "predictedClass": "Down",
          "predictedProbability": 63,
          "binnedConfidence": 2
        },
        "poolMeta": null,
        "mu": 94.18602,
        "sigma": 1.9774,
        "count": 892,
        "outlier": true,
        "underlyingTokens": [
          "So11111111111111111111111111111111111111112",
          "EPjFWdd5AufqSSqeM2qN1xzybapC8G4wEGGkZwyTDt1v"
        ],
        "il7d": null,
        "apyBase7d": 64.54015,
        "apyMean30d": 78.84774,
        "volumeUsd1d": 138248939.05617,
        "volumeUsd7d": 911882699.80131,
        "apyBaseInception": null,
        "type": "lp",
        "weight": 0.2
      },
      {
        "chain": "Base",
        "project": "pancakeswap-amm-v3",
        "symbol": "WETH-USDC",
        "tvlUsd": 2128033,
        "apyBase": 66.97196,
        "apyReward": null,
        "apy": 66.97196,
        "rewardTokens": null,
        "pool": "42146a39-080e-4af1-8318-ad857f68b565",
        "apyPct1D": 3.12044,
        "apyPct7D": -14.62644,
        "apyPct30D": 16.37662,
        "stablecoin": false,
        "ilRisk": "yes",
        "exposure": "multi",
        "predictions": {
          "predictedClass": "Stable/Up",
          "predictedProbability": 53,
          "binnedConfidence": 1
        },
        "poolMeta": "0.05%",
        "mu": 100.04706,
        "sigma": 2.03119,
        "count": 345,
        "outlier": true,
        "underlyingTokens": [
          "0x4200000000000000000000000000000000000006",
          "0x833589fcd6edb6e08f4c7c32d4f71b54bda02913"
        ],
        "il7d": null,
        "apyBase7d": null,
        "apyMean30d": 73.26324,
        "volumeUsd1d": 7809234.85686,
        "volumeUsd7d": 50161844.42652,
        "apyBaseInception": null,
        "type": "lp",
        "weight": 0.2
      },
      {
        "chain": "Base",
        "project": "pancakeswap-amm-v3",
        "symbol": "WETH-USDC",
        "tvlUsd": 4739299,
        "apyBase": 60.17685,
        "apyReward": null,
        "apy": 60.17685,
        "rewardTokens": null,
        "pool": "f6bf9f50-2c82-4dcc-a603-11f9785d88c0",
        "apyPct1D": 6.21695,
        "apyPct7D": -7.36228,
        "apyPct30D": 13.91277,
        "stablecoin": false,
        "ilRisk": "yes",
        "exposure": "multi",
        "predictions": {
          "predictedClass": "Stable/Up",
          "predictedProbability": 56.99999999999999,
          "binnedConfidence": 1
        },
        "poolMeta": "0.01%",
        "mu": 100.96346,
        "sigma": 1.65017,
        "count": 345,
        "outlier": true,
        "underlyingTokens": [
          "0x4200000000000000000000000000000000000006",
          "0x833589fcd6edb6e08f4c7c32d4f71b54bda02913"
        ],
        "il7d": null,
        "apyBase7d": null,
        "apyMean30d": 59.76732,
        "volumeUsd1d": 78135921.665,
        "volumeUsd7d": 483477342.58387,
        "apyBaseInception": null,
        "type": "lp",
        "weight": 0.2
      },
      {
        "chain": "Ethereum",
        "project": "uniswap-v4",
        "symbol": "WBTC-USDC",
        "tvlUsd": 8396157,
        "apyBase": 57.04013,
        "apyReward": null,
        "apy": 57.04013,
        "rewardTokens": null,
        "pool": "fe9309a2-1fc3-4cde-880c-629e1f7ee5e2",
        "apyPct1D": 23.37553,
        "apyPct7D": -10.957,
        "apyPct30D": 42.04424,
        "stablecoin": false,
        "ilRisk": "yes",
        "exposure": "multi",
        "predictions": {
          "predictedClass": "Down",
          "predictedProbability": 97,
          "binnedConfidence": 3
        },
        "poolMeta": "0.30%",
        "mu": 24.32885,
        "sigma": 0.85933,
        "count": 81,
        "outlier": false,
        "underlyingTokens": [
          "0x2260fac5e5542a773aa44fbcfedf7c193bc2c599",
          "0xa0b86991c6218b36c1d19d4a2e9eb0ce3606eb48"
        ],
        "il7d": null,
        "apyBase7d": null,
        "apyMean30d": 37.97967,
        "volumeUsd1d": 4373679.19364,
        "volumeUsd7d": null,
        "apyBaseInception": null,
        "type": "lp",
        "weight": 0.2
      }
    ],
    "virtualBalance": 2503.6193559809285,
    "totalEarned": 3.6193559809292886,
    "snapshots": [
      {
        "ts": "2026-03-19T10:42:16.457Z",
        "balance": 2500
      },
      {
        "ts": "2026-03-19T10:58:27.948Z",
        "balance": 2500.0461944124527
      },
      {
        "ts": "2026-03-19T19:18:56.239Z",
        "balance": 2501.474040125598
      },
      {
        "ts": "2026-03-20T00:03:24.300Z",
        "balance": 2502.4512376012112
      },
      {
        "ts": "2026-03-20T00:03:38.864Z",
        "balance": 2502.4520278129044
      },
      {
        "ts": "2026-03-20T03:04:00.183Z",
        "balance": 2503.039169587914
      },
      {
        "ts": "2026-03-20T06:03:59.989Z",
        "balance": 2503.6193559809285
      }
    ]
  },
  "strategyB": {
    "name": "Risk-Adjusted",
    "positions": [
      {
        "chain": "Solana",
        "project": "jupiter-lend",
        "symbol": "USDS",
        "tvlUsd": 28281259,
        "apyBase": 2.14257,
        "apyReward": 2.95263,
        "apy": 5.0952,
        "rewardTokens": [
          "USDSwr9ApdHk5bvJKMjzff41FfuX8bSxdKcR81vTwcA"
        ],
        "pool": "0d01dc1f-7c3e-46e2-af40-6ec4454c93f0",
        "apyPct1D": -0.01022,
        "apyPct7D": 0.19461,
        "apyPct30D": null,
        "stablecoin": true,
        "ilRisk": "no",
        "exposure": "single",
        "predictions": {
          "predictedClass": "Stable/Up",
          "predictedProbability": 56.99999999999999,
          "binnedConfidence": 1
        },
        "poolMeta": "Earn",
        "mu": 4.93378,
        "sigma": 0.01186,
        "count": 22,
        "outlier": false,
        "underlyingTokens": [
          "USDSwr9ApdHk5bvJKMjzff41FfuX8bSxdKcR81vTwcA"
        ],
        "il7d": null,
        "apyBase7d": null,
        "apyMean30d": 4.91123,
        "volumeUsd1d": null,
        "volumeUsd7d": null,
        "apyBaseInception": null,
        "type": "lending",
        "weight": 0.2
      },
      {
        "chain": "Ethereum",
        "project": "fluid-lending",
        "symbol": "USDT",
        "tvlUsd": 142171395,
        "apyBase": 2.45,
        "apyReward": 1.95,
        "apy": 4.4,
        "rewardTokens": [
          "0xdAC17F958D2ee523a2206206994597C13D831ec7",
          "0x6f40d4a6237c257fff2db00fa0510deeecd303eb"
        ],
        "pool": "4e8cc592-c8d5-4824-8155-128ba521e903",
        "apyPct1D": 0.33,
        "apyPct7D": 0.64,
        "apyPct30D": 0.72,
        "stablecoin": true,
        "ilRisk": "no",
        "exposure": "single",
        "predictions": {
          "predictedClass": "Stable/Up",
          "predictedProbability": 84,
          "binnedConfidence": 3
        },
        "poolMeta": null,
        "mu": 8.2175,
        "sigma": 0.18873,
        "count": 659,
        "outlier": false,
        "underlyingTokens": [
          "0xdAC17F958D2ee523a2206206994597C13D831ec7"
        ],
        "il7d": null,
        "apyBase7d": null,
        "apyMean30d": 3.95293,
        "volumeUsd1d": null,
        "volumeUsd7d": null,
        "apyBaseInception": null,
        "type": "lending",
        "weight": 0.2
      },
      {
        "chain": "Solana",
        "project": "orca-dex",
        "symbol": "SOL-USDC",
        "tvlUsd": 29462739,
        "apyBase": 68.52923,
        "apyReward": 0,
        "apy": 68.52923,
        "rewardTokens": null,
        "pool": "a5c85bc8-eb41-45c0-a520-d18d7529c0d8",
        "apyPct1D": -6.00466,
        "apyPct7D": -18.17925,
        "apyPct30D": -2.88982,
        "stablecoin": false,
        "ilRisk": "yes",
        "exposure": "multi",
        "predictions": {
          "predictedClass": "Down",
          "predictedProbability": 63,
          "binnedConfidence": 2
        },
        "poolMeta": null,
        "mu": 94.18602,
        "sigma": 1.9774,
        "count": 892,
        "outlier": true,
        "underlyingTokens": [
          "So11111111111111111111111111111111111111112",
          "EPjFWdd5AufqSSqeM2qN1xzybapC8G4wEGGkZwyTDt1v"
        ],
        "il7d": null,
        "apyBase7d": 64.54015,
        "apyMean30d": 78.84774,
        "volumeUsd1d": 138248939.05617,
        "volumeUsd7d": 911882699.80131,
        "apyBaseInception": null,
        "type": "lp",
        "score": 0.5997228846604189,
        "weight": 0.2
      },
      {
        "chain": "Ethereum",
        "project": "uniswap-v3",
        "symbol": "USDC-WETH",
        "tvlUsd": 93404962,
        "apyBase": 50.4777,
        "apyReward": null,
        "apy": 50.4777,
        "rewardTokens": null,
        "pool": "665dc8bc-c79d-4800-97f7-304bf368e547",
        "apyPct1D": 16.67543,
        "apyPct7D": -9.41879,
        "apyPct30D": 2.37921,
        "stablecoin": false,
        "ilRisk": "yes",
        "exposure": "multi",
        "predictions": {
          "predictedClass": "Down",
          "predictedProbability": 83,
          "binnedConfidence": 3
        },
        "poolMeta": "0.05%",
        "mu": 29.63167,
        "sigma": 0.9117,
        "count": 1425,
        "outlier": false,
        "underlyingTokens": [
          "0xa0b86991c6218b36c1d19d4a2e9eb0ce3606eb48",
          "0xc02aaa39b223fe8d0a0e5c4f27ead9083c756cc2"
        ],
        "il7d": null,
        "apyBase7d": 16.81345,
        "apyMean30d": 47.70195,
        "volumeUsd1d": 258348912.09558,
        "volumeUsd7d": 990342256.69165,
        "apyBaseInception": null,
        "type": "lp",
        "score": 0.545362118944162,
        "weight": 0.2
      },
      {
        "chain": "Ethereum",
        "project": "uniswap-v4",
        "symbol": "WBTC-USDC",
        "tvlUsd": 8396157,
        "apyBase": 57.04013,
        "apyReward": null,
        "apy": 57.04013,
        "rewardTokens": null,
        "pool": "fe9309a2-1fc3-4cde-880c-629e1f7ee5e2",
        "apyPct1D": 23.37553,
        "apyPct7D": -10.957,
        "apyPct30D": 42.04424,
        "stablecoin": false,
        "ilRisk": "yes",
        "exposure": "multi",
        "predictions": {
          "predictedClass": "Down",
          "predictedProbability": 97,
          "binnedConfidence": 3
        },
        "poolMeta": "0.30%",
        "mu": 24.32885,
        "sigma": 0.85933,
        "count": 81,
        "outlier": false,
        "underlyingTokens": [
          "0x2260fac5e5542a773aa44fbcfedf7c193bc2c599",
          "0xa0b86991c6218b36c1d19d4a2e9eb0ce3606eb48"
        ],
        "il7d": null,
        "apyBase7d": null,
        "apyMean30d": 37.97967,
        "volumeUsd1d": 4373679.19364,
        "volumeUsd7d": null,
        "apyBaseInception": null,
        "type": "lp",
        "score": 0.4643102101017647,
        "weight": 0.2
      }
    ],
    "virtualBalance": 2502.1839436634655,
    "totalEarned": 2.1839436634655964,
    "snapshots": [
      {
        "ts": "2026-03-19T10:42:16.457Z",
        "balance": 2500
      },
      {
        "ts": "2026-03-19T10:58:27.948Z",
        "balance": 2500.029501990763
      },
      {
        "ts": "2026-03-19T19:18:56.239Z",
        "balance": 2500.941393468619
      },
      {
        "ts": "2026-03-20T00:03:24.300Z",
        "balance": 2501.4893077505244
      },
      {
        "ts": "2026-03-20T00:03:38.864Z",
        "balance": 2501.4897780988667
      },
      {
        "ts": "2026-03-20T03:04:00.183Z",
        "balance": 2501.8392555401283
      },
      {
        "ts": "2026-03-20T06:03:59.989Z",
        "balance": 2502.1839436634655
      }
    ]
  },
  "cycles": 7,
  "history": [],
  "apyAlerts": []
}